talos_mcp/__init__.py
talos_mcp/cache.py
talos_mcp/cli.py
talos_mcp/config.py
talos_mcp/idempotency.py
talos_mcp/domain/__init__.py
talos_mcp/domain/tool_policy.py
talos_mcp/transport/__init__.py
talos_mcp/transport/base.py
talos_mcp/transport/http.py
talos_mcp/transport/stdio.py
talos_mcp/transport/talos_tunnel.py
talos_mcp_connector-0.1.0.dist-info/licenses/LICENSE
talos_mcp_connector-0.1.0.dist-info/licenses/NOTICE
talos_mcp_connector-0.1.0.dist-info/METADATA
talos_mcp_connector-0.1.0.dist-info/WHEEL
talos_mcp_connector-0.1.0.dist-info/entry_points.txt
talos_mcp_connector-0.1.0.dist-info/top_level.txt
talos_mcp_connector-0.1.0.dist-info/RECORD
