Metadata-Version: 2.4
Name: talos-mcp-connector
Version: 0.1.0
Summary: Talos MCP Connector CLI
License-Expression: Apache-2.0
Requires-Python: >=3.10
License-File: LICENSE
License-File: NOTICE
Requires-Dist: click>=8.1.0
Requires-Dist: pydantic>=2.0.0
Requires-Dist: pyyaml>=6.0
Requires-Dist: requests>=2.31.0
Requires-Dist: jsonschema>=4.0.0
Requires-Dist: jsonpointer>=3.0.0
Requires-Dist: rich>=13.0.0
Provides-Extra: dev
Requires-Dist: pytest; extra == "dev"
Requires-Dist: ruff; extra == "dev"
Requires-Dist: types-PyYAML; extra == "dev"
Requires-Dist: types-jsonschema; extra == "dev"
Dynamic: license-file
